pyhg19/ENCFF001TDO.bed.gz
pyhg19/__init__.py
pyhg19/pyhg19.py
pyhg19-1.0.3.dist-info/LICENSE
pyhg19-1.0.3.dist-info/METADATA
pyhg19-1.0.3.dist-info/WHEEL
pyhg19-1.0.3.dist-info/top_level.txt
pyhg19-1.0.3.dist-info/RECORD
