Metadata-Version: 2.1
Name: pyhg19
Version: 1.0.3
Summary: Utilities for working with human genome build hg19
Home-page: https://gitlab.com/aaylward/pyhg19
Author: Anthony Aylward
Author-email: aaylward@salk.edu
License: UNKNOWN
Platform: UNKNOWN
Classifier: Programming Language :: Python :: 3
Classifier: License :: OSI Approved :: MIT License
Classifier: Operating System :: OS Independent
License-File: LICENSE
Requires-Dist: pydbsnp
